embedmd/__init__.py
embedmd/core.py
embedmd/html.py
embedmd/md.py
embedmd-0.8.2.dist-info/METADATA
embedmd-0.8.2.dist-info/WHEEL
embedmd-0.8.2.dist-info/entry_points.txt
embedmd-0.8.2.dist-info/top_level.txt
embedmd-0.8.2.dist-info/RECORD
