Metadata-Version: 2.1
Name: embedmd
Version: 0.8.2
Summary: Embed markdown files into html
Home-page: https://github.com/kylepollina/embedmd
Author: Kyle Pollina
Author-email: kylepollina@pm.me
License: UNKNOWN
Platform: UNKNOWN
Classifier: Programming Language :: Python :: 3
Classifier: Programming Language :: Python :: 3.7
Requires-Dist: markdown
Requires-Dist: argparse-ext
